Metadata-Version: 2.1
Name: ovos-PHAL-plugin-camera
Version: 0.2.1
Summary: Expose camera to OVOS
Home-page: https://github.com/OpenVoiceOS/ovos-PHAL-plugin-camera
Author: JarbasAi
Author-email: jarbasai@mailfence.com
License: Apache-2.0
Classifier: License :: OSI Approved :: Apache Software License
Requires-Dist: ovos-plugin-manager<2.0.0
Requires-Dist: imutils
Requires-Dist: opencv-python
Requires-Dist: flask
Requires-Dist: pybase64
Requires-Dist: picamera2; sys_platform == "linux" and (platform_machine == "armv7l" or platform_machine == "aarch64")
